{"primaryContentSections":[{"kind":"declarations","declarations":[{"tokens":[{"kind":"keyword","text":"static"},{"kind":"text","text":" "},{"kind":"keyword","text":"func"},{"kind":"text","text":" "},{"kind":"identifier","text":"buildBlock"},{"kind":"text","text":"<"},{"kind":"genericParameter","text":"T0"},{"kind":"text","text":", "},{"kind":"genericParameter","text":"T1"},{"kind":"text","text":", "},{"kind":"genericParameter","text":"T2"},{"kind":"text","text":", "},{"kind":"genericParameter","text":"T3"},{"kind":"text","text":", "},{"kind":"genericParameter","text":"T4"},{"kind":"text","text":", "},{"kind":"genericParameter","text":"T5"},{"kind":"text","text":", "},{"kind":"genericParameter","text":"T6"},{"kind":"text","text":", "},{"kind":"genericParameter","text":"T7"},{"kind":"text","text":", "},{"kind":"genericParameter","text":"T8"},{"kind":"text","text":", "},{"kind":"genericParameter","text":"T9"},{"kind":"text","text":", "},{"kind":"genericParameter","text":"T10"},{"kind":"text","text":", "},{"kind":"genericParameter","text":"T11"},{"kind":"text","text":", "},{"kind":"genericParameter","text":"T12"},{"kind":"text","text":", "},{"kind":"genericParameter","text":"T13"},{"kind":"text","text":", "},{"kind":"genericParameter","text":"T14"},{"kind":"text","text":", "},{"kind":"genericParameter","text":"T15"},{"kind":"text","text":", "},{"kind":"genericParameter","text":"T16"},{"kind":"text","text":", "},{"kind":"genericParameter","text":"T17"},{"kind":"text","text":", "},{"kind":"genericParameter","text":"T18"},{"kind":"text","text":", "},{"kind":"genericParameter","text":"T19"},{"kind":"text","text":", "},{"kind":"genericParameter","text":"T20"},{"kind":"text","text":", "},{"kind":"genericParameter","text":"T21"},{"kind":"text","text":", "},{"kind":"genericParameter","text":"T22"},{"kind":"text","text":", "},{"kind":"genericParameter","text":"T23"},{"kind":"text","text":", "},{"kind":"genericParameter","text":"T24"},{"kind":"text","text":", "},{"kind":"genericParameter","text":"T25"},{"kind":"text","text":", "},{"kind":"genericParameter","text":"T26"},{"kind":"text","text":", "},{"kind":"genericParameter","text":"T27"},{"kind":"text","text":", "},{"kind":"genericParameter","text":"T28"},{"kind":"text","text":", "},{"kind":"genericParameter","text":"T29"},{"kind":"text","text":", "},{"kind":"genericParameter","text":"T30"},{"kind":"text","text":", "},{"kind":"genericParameter","text":"T31"},{"kind":"text","text":", "},{"kind":"genericParameter","text":"T32"},{"kind":"text","text":", "},{"kind":"genericParameter","text":"T33"},{"kind":"text","text":", "},{"kind":"genericParameter","text":"T34"},{"kind":"text","text":", "},{"kind":"genericParameter","text":"T35"},{"kind":"text","text":", "},{"kind":"genericParameter","text":"T36"},{"kind":"text","text":", "},{"kind":"genericParameter","text":"T37"},{"kind":"text","text":", "},{"kind":"genericParameter","text":"T38"},{"kind":"text","text":", "},{"kind":"genericParameter","text":"T39"},{"kind":"text","text":", "},{"kind":"genericParameter","text":"T40"},{"kind":"text","text":", "},{"kind":"genericParameter","text":"T41"},{"kind":"text","text":", "},{"kind":"genericParameter","text":"T42"},{"kind":"text","text":", "},{"kind":"genericParameter","text":"T43"},{"kind":"text","text":", "},{"kind":"genericParameter","text":"T44"},{"kind":"text","text":", "},{"kind":"genericParameter","text":"T45"},{"kind":"text","text":", "},{"kind":"genericParameter","text":"T46"},{"kind":"text","text":", "},{"kind":"genericParameter","text":"T47"},{"kind":"text","text":", "},{"kind":"genericParameter","text":"T48"},{"kind":"text","text":", "},{"kind":"genericParameter","text":"T49"},{"kind":"text","text":", "},{"kind":"genericParameter","text":"T50"},{"kind":"text","text":", "},{"kind":"genericParameter","text":"T51"},{"kind":"text","text":", "},{"kind":"genericParameter","text":"T52"},{"kind":"text","text":", "},{"kind":"genericParameter","text":"T53"},{"kind":"text","text":", "},{"kind":"genericParameter","text":"T54"},{"kind":"text","text":", "},{"kind":"genericParameter","text":"T55"},{"kind":"text","text":", "},{"kind":"genericParameter","text":"T56"},{"kind":"text","text":", "},{"kind":"genericParameter","text":"T57"},{"kind":"text","text":", "},{"kind":"genericParameter","text":"T58"},{"kind":"text","text":", "},{"kind":"genericParameter","text":"T59"},{"kind":"text","text":">("},{"kind":"externalParam","text":"_"},{"kind":"text","text":" "},{"kind":"internalParam","text":"arg0"},{"kind":"text","text":": "},{"kind":"typeIdentifier","text":"T0"},{"kind":"text","text":", "},{"kind":"externalParam","text":"_"},{"kind":"text","text":" "},{"kind":"internalParam","text":"arg1"},{"kind":"text","text":": "},{"kind":"typeIdentifier","text":"T1"},{"kind":"text","text":", "},{"kind":"externalParam","text":"_"},{"kind":"text","text":" "},{"kind":"internalParam","text":"arg2"},{"kind":"text","text":": "},{"kind":"typeIdentifier","text":"T2"},{"kind":"text","text":", "},{"kind":"externalParam","text":"_"},{"kind":"text","text":" "},{"kind":"internalParam","text":"arg3"},{"kind":"text","text":": "},{"kind":"typeIdentifier","text":"T3"},{"kind":"text","text":", "},{"kind":"externalParam","text":"_"},{"kind":"text","text":" "},{"kind":"internalParam","text":"arg4"},{"kind":"text","text":": "},{"kind":"typeIdentifier","text":"T4"},{"kind":"text","text":", "},{"kind":"externalParam","text":"_"},{"kind":"text","text":" "},{"kind":"internalParam","text":"arg5"},{"kind":"text","text":": "},{"kind":"typeIdentifier","text":"T5"},{"kind":"text","text":", "},{"kind":"externalParam","text":"_"},{"kind":"text","text":" "},{"kind":"internalParam","text":"arg6"},{"kind":"text","text":": "},{"kind":"typeIdentifier","text":"T6"},{"kind":"text","text":", "},{"kind":"externalParam","text":"_"},{"kind":"text","text":" "},{"kind":"internalParam","text":"arg7"},{"kind":"text","text":": "},{"kind":"typeIdentifier","text":"T7"},{"kind":"text","text":", "},{"kind":"externalParam","text":"_"},{"kind":"text","text":" "},{"kind":"internalParam","text":"arg8"},{"kind":"text","text":": "},{"kind":"typeIdentifier","text":"T8"},{"kind":"text","text":", "},{"kind":"externalParam","text":"_"},{"kind":"text","text":" "},{"kind":"internalParam","text":"arg9"},{"kind":"text","text":": "},{"kind":"typeIdentifier","text":"T9"},{"kind":"text","text":", "},{"kind":"externalParam","text":"_"},{"kind":"text","text":" "},{"kind":"internalParam","text":"arg10"},{"kind":"text","text":": "},{"kind":"typeIdentifier","text":"T10"},{"kind":"text","text":", "},{"kind":"externalParam","text":"_"},{"kind":"text","text":" "},{"kind":"internalParam","text":"arg11"},{"kind":"text","text":": "},{"kind":"typeIdentifier","text":"T11"},{"kind":"text","text":", "},{"kind":"externalParam","text":"_"},{"kind":"text","text":" "},{"kind":"internalParam","text":"arg12"},{"kind":"text","text":": "},{"kind":"typeIdentifier","text":"T12"},{"kind":"text","text":", "},{"kind":"externalParam","text":"_"},{"kind":"text","text":" "},{"kind":"internalParam","text":"arg13"},{"kind":"text","text":": "},{"kind":"typeIdentifier","text":"T13"},{"kind":"text","text":", "},{"kind":"externalParam","text":"_"},{"kind":"text","text":" "},{"kind":"internalParam","text":"arg14"},{"kind":"text","text":": "},{"kind":"typeIdentifier","text":"T14"},{"kind":"text","text":", "},{"kind":"externalParam","text":"_"},{"kind":"text","text":" "},{"kind":"internalParam","text":"arg15"},{"kind":"text","text":": "},{"kind":"typeIdentifier","text":"T15"},{"kind":"text","text":", "},{"kind":"externalParam","text":"_"},{"kind":"text","text":" "},{"kind":"internalParam","text":"arg16"},{"kind":"text","text":": "},{"kind":"typeIdentifier","text":"T16"},{"kind":"text","text":", "},{"kind":"externalParam","text":"_"},{"kind":"text","text":" "},{"kind":"internalParam","text":"arg17"},{"kind":"text","text":": "},{"kind":"typeIdentifier","text":"T17"},{"kind":"text","text":", "},{"kind":"externalParam","text":"_"},{"kind":"text","text":" "},{"kind":"internalParam","text":"arg18"},{"kind":"text","text":": "},{"kind":"typeIdentifier","text":"T18"},{"kind":"text","text":", "},{"kind":"externalParam","text":"_"},{"kind":"text","text":" "},{"kind":"internalParam","text":"arg19"},{"kind":"text","text":": "},{"kind":"typeIdentifier","text":"T19"},{"kind":"text","text":", "},{"kind":"externalParam","text":"_"},{"kind":"text","text":" "},{"kind":"internalParam","text":"arg20"},{"kind":"text","text":": "},{"kind":"typeIdentifier","text":"T20"},{"kind":"text","text":", "},{"kind":"externalParam","text":"_"},{"kind":"text","text":" "},{"kind":"internalParam","text":"arg21"},{"kind":"text","text":": "},{"kind":"typeIdentifier","text":"T21"},{"kind":"text","text":", "},{"kind":"externalParam","text":"_"},{"kind":"text","text":" "},{"kind":"internalParam","text":"arg22"},{"kind":"text","text":": "},{"kind":"typeIdentifier","text":"T22"},{"kind":"text","text":", "},{"kind":"externalParam","text":"_"},{"kind":"text","text":" "},{"kind":"internalParam","text":"arg23"},{"kind":"text","text":": "},{"kind":"typeIdentifier","text":"T23"},{"kind":"text","text":", "},{"kind":"externalParam","text":"_"},{"kind":"text","text":" "},{"kind":"internalParam","text":"arg24"},{"kind":"text","text":": "},{"kind":"typeIdentifier","text":"T24"},{"kind":"text","text":", "},{"kind":"externalParam","text":"_"},{"kind":"text","text":" "},{"kind":"internalParam","text":"arg25"},{"kind":"text","text":": "},{"kind":"typeIdentifier","text":"T25"},{"kind":"text","text":", "},{"kind":"externalParam","text":"_"},{"kind":"text","text":" "},{"kind":"internalParam","text":"arg26"},{"kind":"text","text":": "},{"kind":"typeIdentifier","text":"T26"},{"kind":"text","text":", "},{"kind":"externalParam","text":"_"},{"kind":"text","text":" "},{"kind":"internalParam","text":"arg27"},{"kind":"text","text":": "},{"kind":"typeIdentifier","text":"T27"},{"kind":"text","text":", "},{"kind":"externalParam","text":"_"},{"kind":"text","text":" "},{"kind":"internalParam","text":"arg28"},{"kind":"text","text":": "},{"kind":"typeIdentifier","text":"T28"},{"kind":"text","text":", "},{"kind":"externalParam","text":"_"},{"kind":"text","text":" "},{"kind":"internalParam","text":"arg29"},{"kind":"text","text":": "},{"kind":"typeIdentifier","text":"T29"},{"kind":"text","text":", "},{"kind":"externalParam","text":"_"},{"kind":"text","text":" "},{"kind":"internalParam","text":"arg30"},{"kind":"text","text":": "},{"kind":"typeIdentifier","text":"T30"},{"kind":"text","text":", "},{"kind":"externalParam","text":"_"},{"kind":"text","text":" "},{"kind":"internalParam","text":"arg31"},{"kind":"text","text":": "},{"kind":"typeIdentifier","text":"T31"},{"kind":"text","text":", "},{"kind":"externalParam","text":"_"},{"kind":"text","text":" "},{"kind":"internalParam","text":"arg32"},{"kind":"text","text":": "},{"kind":"typeIdentifier","text":"T32"},{"kind":"text","text":", "},{"kind":"externalParam","text":"_"},{"kind":"text","text":" "},{"kind":"internalParam","text":"arg33"},{"kind":"text","text":": "},{"kind":"typeIdentifier","text":"T33"},{"kind":"text","text":", "},{"kind":"externalParam","text":"_"},{"kind":"text","text":" "},{"kind":"internalParam","text":"arg34"},{"kind":"text","text":": "},{"kind":"typeIdentifier","text":"T34"},{"kind":"text","text":", "},{"kind":"externalParam","text":"_"},{"kind":"text","text":" "},{"kind":"internalParam","text":"arg35"},{"kind":"text","text":": "},{"kind":"typeIdentifier","text":"T35"},{"kind":"text","text":", "},{"kind":"externalParam","text":"_"},{"kind":"text","text":" "},{"kind":"internalParam","text":"arg36"},{"kind":"text","text":": "},{"kind":"typeIdentifier","text":"T36"},{"kind":"text","text":", "},{"kind":"externalParam","text":"_"},{"kind":"text","text":" "},{"kind":"internalParam","text":"arg37"},{"kind":"text","text":": "},{"kind":"typeIdentifier","text":"T37"},{"kind":"text","text":", "},{"kind":"externalParam","text":"_"},{"kind":"text","text":" "},{"kind":"internalParam","text":"arg38"},{"kind":"text","text":": "},{"kind":"typeIdentifier","text":"T38"},{"kind":"text","text":", "},{"kind":"externalParam","text":"_"},{"kind":"text","text":" "},{"kind":"internalParam","text":"arg39"},{"kind":"text","text":": "},{"kind":"typeIdentifier","text":"T39"},{"kind":"text","text":", "},{"kind":"externalParam","text":"_"},{"kind":"text","text":" "},{"kind":"internalParam","text":"arg40"},{"kind":"text","text":": "},{"kind":"typeIdentifier","text":"T40"},{"kind":"text","text":", "},{"kind":"externalParam","text":"_"},{"kind":"text","text":" "},{"kind":"internalParam","text":"arg41"},{"kind":"text","text":": "},{"kind":"typeIdentifier","text":"T41"},{"kind":"text","text":", "},{"kind":"externalParam","text":"_"},{"kind":"text","text":" "},{"kind":"internalParam","text":"arg42"},{"kind":"text","text":": "},{"kind":"typeIdentifier","text":"T42"},{"kind":"text","text":", "},{"kind":"externalParam","text":"_"},{"kind":"text","text":" "},{"kind":"internalParam","text":"arg43"},{"kind":"text","text":": "},{"kind":"typeIdentifier","text":"T43"},{"kind":"text","text":", "},{"kind":"externalParam","text":"_"},{"kind":"text","text":" "},{"kind":"internalParam","text":"arg44"},{"kind":"text","text":": "},{"kind":"typeIdentifier","text":"T44"},{"kind":"text","text":", "},{"kind":"externalParam","text":"_"},{"kind":"text","text":" "},{"kind":"internalParam","text":"arg45"},{"kind":"text","text":": "},{"kind":"typeIdentifier","text":"T45"},{"kind":"text","text":", "},{"kind":"externalParam","text":"_"},{"kind":"text","text":" "},{"kind":"internalParam","text":"arg46"},{"kind":"text","text":": "},{"kind":"typeIdentifier","text":"T46"},{"kind":"text","text":", "},{"kind":"externalParam","text":"_"},{"kind":"text","text":" "},{"kind":"internalParam","text":"arg47"},{"kind":"text","text":": "},{"kind":"typeIdentifier","text":"T47"},{"kind":"text","text":", "},{"kind":"externalParam","text":"_"},{"kind":"text","text":" "},{"kind":"internalParam","text":"arg48"},{"kind":"text","text":": "},{"kind":"typeIdentifier","text":"T48"},{"kind":"text","text":", "},{"kind":"externalParam","text":"_"},{"kind":"text","text":" "},{"kind":"internalParam","text":"arg49"},{"kind":"text","text":": "},{"kind":"typeIdentifier","text":"T49"},{"kind":"text","text":", "},{"kind":"externalParam","text":"_"},{"kind":"text","text":" "},{"kind":"internalParam","text":"arg50"},{"kind":"text","text":": "},{"kind":"typeIdentifier","text":"T50"},{"kind":"text","text":", "},{"kind":"externalParam","text":"_"},{"kind":"text","text":" "},{"kind":"internalParam","text":"arg51"},{"kind":"text","text":": "},{"kind":"typeIdentifier","text":"T51"},{"kind":"text","text":", "},{"kind":"externalParam","text":"_"},{"kind":"text","text":" "},{"kind":"internalParam","text":"arg52"},{"kind":"text","text":": "},{"kind":"typeIdentifier","text":"T52"},{"kind":"text","text":", "},{"kind":"externalParam","text":"_"},{"kind":"text","text":" "},{"kind":"internalParam","text":"arg53"},{"kind":"text","text":": "},{"kind":"typeIdentifier","text":"T53"},{"kind":"text","text":", "},{"kind":"externalParam","text":"_"},{"kind":"text","text":" "},{"kind":"internalParam","text":"arg54"},{"kind":"text","text":": "},{"kind":"typeIdentifier","text":"T54"},{"kind":"text","text":", "},{"kind":"externalParam","text":"_"},{"kind":"text","text":" "},{"kind":"internalParam","text":"arg55"},{"kind":"text","text":": "},{"kind":"typeIdentifier","text":"T55"},{"kind":"text","text":", "},{"kind":"externalParam","text":"_"},{"kind":"text","text":" "},{"kind":"internalParam","text":"arg56"},{"kind":"text","text":": "},{"kind":"typeIdentifier","text":"T56"},{"kind":"text","text":", "},{"kind":"externalParam","text":"_"},{"kind":"text","text":" "},{"kind":"internalParam","text":"arg57"},{"kind":"text","text":": "},{"kind":"typeIdentifier","text":"T57"},{"kind":"text","text":", "},{"kind":"externalParam","text":"_"},{"kind":"text","text":" "},{"kind":"internalParam","text":"arg58"},{"kind":"text","text":": "},{"kind":"typeIdentifier","text":"T58"},{"kind":"text","text":", "},{"kind":"externalParam","text":"_"},{"kind":"text","text":" "},{"kind":"internalParam","text":"arg59"},{"kind":"text","text":": "},{"kind":"typeIdentifier","text":"T59"},{"kind":"text","text":") -> "},{"kind":"keyword","text":"some"},{"kind":"text","text":" "},{"kind":"typeIdentifier","identifier":"doc:\/\/Apodini\/documentation\/Apodini\/Component","preciseIdentifier":"s:7Apodini9ComponentP","text":"Component"},{"kind":"text","text":" "},{"kind":"keyword","text":"where"},{"kind":"text","text":" "},{"kind":"typeIdentifier","text":"T0"},{"kind":"text","text":" : "},{"kind":"typeIdentifier","identifier":"doc:\/\/Apodini\/documentation\/Apodini\/Component","preciseIdentifier":"s:7Apodini9ComponentP","text":"Component"},{"kind":"text","text":", "},{"kind":"typeIdentifier","text":"T1"},{"kind":"text","text":" : "},{"kind":"typeIdentifier","identifier":"doc:\/\/Apodini\/documentation\/Apodini\/Component","preciseIdentifier":"s:7Apodini9ComponentP","text":"Component"},{"kind":"text","text":", "},{"kind":"typeIdentifier","text":"T2"},{"kind":"text","text":" : "},{"kind":"typeIdentifier","identifier":"doc:\/\/Apodini\/documentation\/Apodini\/Component","preciseIdentifier":"s:7Apodini9ComponentP","text":"Component"},{"kind":"text","text":", "},{"kind":"typeIdentifier","text":"T3"},{"kind":"text","text":" : "},{"kind":"typeIdentifier","identifier":"doc:\/\/Apodini\/documentation\/Apodini\/Component","preciseIdentifier":"s:7Apodini9ComponentP","text":"Component"},{"kind":"text","text":", "},{"kind":"typeIdentifier","text":"T4"},{"kind":"text","text":" : "},{"kind":"typeIdentifier","identifier":"doc:\/\/Apodini\/documentation\/Apodini\/Component","preciseIdentifier":"s:7Apodini9ComponentP","text":"Component"},{"kind":"text","text":", "},{"kind":"typeIdentifier","text":"T5"},{"kind":"text","text":" : "},{"kind":"typeIdentifier","identifier":"doc:\/\/Apodini\/documentation\/Apodini\/Component","preciseIdentifier":"s:7Apodini9ComponentP","text":"Component"},{"kind":"text","text":", "},{"kind":"typeIdentifier","text":"T6"},{"kind":"text","text":" : "},{"kind":"typeIdentifier","identifier":"doc:\/\/Apodini\/documentation\/Apodini\/Component","preciseIdentifier":"s:7Apodini9ComponentP","text":"Component"},{"kind":"text","text":", "},{"kind":"typeIdentifier","text":"T7"},{"kind":"text","text":" : "},{"kind":"typeIdentifier","identifier":"doc:\/\/Apodini\/documentation\/Apodini\/Component","preciseIdentifier":"s:7Apodini9ComponentP","text":"Component"},{"kind":"text","text":", "},{"kind":"typeIdentifier","text":"T8"},{"kind":"text","text":" : "},{"kind":"typeIdentifier","identifier":"doc:\/\/Apodini\/documentation\/Apodini\/Component","preciseIdentifier":"s:7Apodini9ComponentP","text":"Component"},{"kind":"text","text":", "},{"kind":"typeIdentifier","text":"T9"},{"kind":"text","text":" : "},{"kind":"typeIdentifier","identifier":"doc:\/\/Apodini\/documentation\/Apodini\/Component","preciseIdentifier":"s:7Apodini9ComponentP","text":"Component"},{"kind":"text","text":", "},{"kind":"typeIdentifier","text":"T10"},{"kind":"text","text":" : "},{"kind":"typeIdentifier","identifier":"doc:\/\/Apodini\/documentation\/Apodini\/Component","preciseIdentifier":"s:7Apodini9ComponentP","text":"Component"},{"kind":"text","text":", "},{"kind":"typeIdentifier","text":"T11"},{"kind":"text","text":" : "},{"kind":"typeIdentifier","identifier":"doc:\/\/Apodini\/documentation\/Apodini\/Component","preciseIdentifier":"s:7Apodini9ComponentP","text":"Component"},{"kind":"text","text":", "},{"kind":"typeIdentifier","text":"T12"},{"kind":"text","text":" : "},{"kind":"typeIdentifier","identifier":"doc:\/\/Apodini\/documentation\/Apodini\/Component","preciseIdentifier":"s:7Apodini9ComponentP","text":"Component"},{"kind":"text","text":", "},{"kind":"typeIdentifier","text":"T13"},{"kind":"text","text":" : "},{"kind":"typeIdentifier","identifier":"doc:\/\/Apodini\/documentation\/Apodini\/Component","preciseIdentifier":"s:7Apodini9ComponentP","text":"Component"},{"kind":"text","text":", "},{"kind":"typeIdentifier","text":"T14"},{"kind":"text","text":" : "},{"kind":"typeIdentifier","identifier":"doc:\/\/Apodini\/documentation\/Apodini\/Component","preciseIdentifier":"s:7Apodini9ComponentP","text":"Component"},{"kind":"text","text":", "},{"kind":"typeIdentifier","text":"T15"},{"kind":"text","text":" : "},{"kind":"typeIdentifier","identifier":"doc:\/\/Apodini\/documentation\/Apodini\/Component","preciseIdentifier":"s:7Apodini9ComponentP","text":"Component"},{"kind":"text","text":", "},{"kind":"typeIdentifier","text":"T16"},{"kind":"text","text":" : "},{"kind":"typeIdentifier","identifier":"doc:\/\/Apodini\/documentation\/Apodini\/Component","preciseIdentifier":"s:7Apodini9ComponentP","text":"Component"},{"kind":"text","text":", "},{"kind":"typeIdentifier","text":"T17"},{"kind":"text","text":" : "},{"kind":"typeIdentifier","identifier":"doc:\/\/Apodini\/documentation\/Apodini\/Component","preciseIdentifier":"s:7Apodini9ComponentP","text":"Component"},{"kind":"text","text":", "},{"kind":"typeIdentifier","text":"T18"},{"kind":"text","text":" : "},{"kind":"typeIdentifier","identifier":"doc:\/\/Apodini\/documentation\/Apodini\/Component","preciseIdentifier":"s:7Apodini9ComponentP","text":"Component"},{"kind":"text","text":", "},{"kind":"typeIdentifier","text":"T19"},{"kind":"text","text":" : "},{"kind":"typeIdentifier","identifier":"doc:\/\/Apodini\/documentation\/Apodini\/Component","preciseIdentifier":"s:7Apodini9ComponentP","text":"Component"},{"kind":"text","text":", "},{"kind":"typeIdentifier","text":"T20"},{"kind":"text","text":" : "},{"kind":"typeIdentifier","identifier":"doc:\/\/Apodini\/documentation\/Apodini\/Component","preciseIdentifier":"s:7Apodini9ComponentP","text":"Component"},{"kind":"text","text":", "},{"kind":"typeIdentifier","text":"T21"},{"kind":"text","text":" : "},{"kind":"typeIdentifier","identifier":"doc:\/\/Apodini\/documentation\/Apodini\/Component","preciseIdentifier":"s:7Apodini9ComponentP","text":"Component"},{"kind":"text","text":", "},{"kind":"typeIdentifier","text":"T22"},{"kind":"text","text":" : "},{"kind":"typeIdentifier","identifier":"doc:\/\/Apodini\/documentation\/Apodini\/Component","preciseIdentifier":"s:7Apodini9ComponentP","text":"Component"},{"kind":"text","text":", "},{"kind":"typeIdentifier","text":"T23"},{"kind":"text","text":" : "},{"kind":"typeIdentifier","identifier":"doc:\/\/Apodini\/documentation\/Apodini\/Component","preciseIdentifier":"s:7Apodini9ComponentP","text":"Component"},{"kind":"text","text":", "},{"kind":"typeIdentifier","text":"T24"},{"kind":"text","text":" : "},{"kind":"typeIdentifier","identifier":"doc:\/\/Apodini\/documentation\/Apodini\/Component","preciseIdentifier":"s:7Apodini9ComponentP","text":"Component"},{"kind":"text","text":", "},{"kind":"typeIdentifier","text":"T25"},{"kind":"text","text":" : "},{"kind":"typeIdentifier","identifier":"doc:\/\/Apodini\/documentation\/Apodini\/Component","preciseIdentifier":"s:7Apodini9ComponentP","text":"Component"},{"kind":"text","text":", "},{"kind":"typeIdentifier","text":"T26"},{"kind":"text","text":" : "},{"kind":"typeIdentifier","identifier":"doc:\/\/Apodini\/documentation\/Apodini\/Component","preciseIdentifier":"s:7Apodini9ComponentP","text":"Component"},{"kind":"text","text":", "},{"kind":"typeIdentifier","text":"T27"},{"kind":"text","text":" : "},{"kind":"typeIdentifier","identifier":"doc:\/\/Apodini\/documentation\/Apodini\/Component","preciseIdentifier":"s:7Apodini9ComponentP","text":"Component"},{"kind":"text","text":", "},{"kind":"typeIdentifier","text":"T28"},{"kind":"text","text":" : "},{"kind":"typeIdentifier","identifier":"doc:\/\/Apodini\/documentation\/Apodini\/Component","preciseIdentifier":"s:7Apodini9ComponentP","text":"Component"},{"kind":"text","text":", "},{"kind":"typeIdentifier","text":"T29"},{"kind":"text","text":" : "},{"kind":"typeIdentifier","identifier":"doc:\/\/Apodini\/documentation\/Apodini\/Component","preciseIdentifier":"s:7Apodini9ComponentP","text":"Component"},{"kind":"text","text":", "},{"kind":"typeIdentifier","text":"T30"},{"kind":"text","text":" : "},{"kind":"typeIdentifier","identifier":"doc:\/\/Apodini\/documentation\/Apodini\/Component","preciseIdentifier":"s:7Apodini9ComponentP","text":"Component"},{"kind":"text","text":", "},{"kind":"typeIdentifier","text":"T31"},{"kind":"text","text":" : "},{"kind":"typeIdentifier","identifier":"doc:\/\/Apodini\/documentation\/Apodini\/Component","preciseIdentifier":"s:7Apodini9ComponentP","text":"Component"},{"kind":"text","text":", "},{"kind":"typeIdentifier","text":"T32"},{"kind":"text","text":" : "},{"kind":"typeIdentifier","identifier":"doc:\/\/Apodini\/documentation\/Apodini\/Component","preciseIdentifier":"s:7Apodini9ComponentP","text":"Component"},{"kind":"text","text":", "},{"kind":"typeIdentifier","text":"T33"},{"kind":"text","text":" : "},{"kind":"typeIdentifier","identifier":"doc:\/\/Apodini\/documentation\/Apodini\/Component","preciseIdentifier":"s:7Apodini9ComponentP","text":"Component"},{"kind":"text","text":", "},{"kind":"typeIdentifier","text":"T34"},{"kind":"text","text":" : "},{"kind":"typeIdentifier","identifier":"doc:\/\/Apodini\/documentation\/Apodini\/Component","preciseIdentifier":"s:7Apodini9ComponentP","text":"Component"},{"kind":"text","text":", "},{"kind":"typeIdentifier","text":"T35"},{"kind":"text","text":" : "},{"kind":"typeIdentifier","identifier":"doc:\/\/Apodini\/documentation\/Apodini\/Component","preciseIdentifier":"s:7Apodini9ComponentP","text":"Component"},{"kind":"text","text":", "},{"kind":"typeIdentifier","text":"T36"},{"kind":"text","text":" : "},{"kind":"typeIdentifier","identifier":"doc:\/\/Apodini\/documentation\/Apodini\/Component","preciseIdentifier":"s:7Apodini9ComponentP","text":"Component"},{"kind":"text","text":", "},{"kind":"typeIdentifier","text":"T37"},{"kind":"text","text":" : "},{"kind":"typeIdentifier","identifier":"doc:\/\/Apodini\/documentation\/Apodini\/Component","preciseIdentifier":"s:7Apodini9ComponentP","text":"Component"},{"kind":"text","text":", "},{"kind":"typeIdentifier","text":"T38"},{"kind":"text","text":" : "},{"kind":"typeIdentifier","identifier":"doc:\/\/Apodini\/documentation\/Apodini\/Component","preciseIdentifier":"s:7Apodini9ComponentP","text":"Component"},{"kind":"text","text":", "},{"kind":"typeIdentifier","text":"T39"},{"kind":"text","text":" : "},{"kind":"typeIdentifier","identifier":"doc:\/\/Apodini\/documentation\/Apodini\/Component","preciseIdentifier":"s:7Apodini9ComponentP","text":"Component"},{"kind":"text","text":", "},{"kind":"typeIdentifier","text":"T40"},{"kind":"text","text":" : "},{"kind":"typeIdentifier","identifier":"doc:\/\/Apodini\/documentation\/Apodini\/Component","preciseIdentifier":"s:7Apodini9ComponentP","text":"Component"},{"kind":"text","text":", "},{"kind":"typeIdentifier","text":"T41"},{"kind":"text","text":" : "},{"kind":"typeIdentifier","identifier":"doc:\/\/Apodini\/documentation\/Apodini\/Component","preciseIdentifier":"s:7Apodini9ComponentP","text":"Component"},{"kind":"text","text":", "},{"kind":"typeIdentifier","text":"T42"},{"kind":"text","text":" : "},{"kind":"typeIdentifier","identifier":"doc:\/\/Apodini\/documentation\/Apodini\/Component","preciseIdentifier":"s:7Apodini9ComponentP","text":"Component"},{"kind":"text","text":", "},{"kind":"typeIdentifier","text":"T43"},{"kind":"text","text":" : "},{"kind":"typeIdentifier","identifier":"doc:\/\/Apodini\/documentation\/Apodini\/Component","preciseIdentifier":"s:7Apodini9ComponentP","text":"Component"},{"kind":"text","text":", "},{"kind":"typeIdentifier","text":"T44"},{"kind":"text","text":" : "},{"kind":"typeIdentifier","identifier":"doc:\/\/Apodini\/documentation\/Apodini\/Component","preciseIdentifier":"s:7Apodini9ComponentP","text":"Component"},{"kind":"text","text":", "},{"kind":"typeIdentifier","text":"T45"},{"kind":"text","text":" : "},{"kind":"typeIdentifier","identifier":"doc:\/\/Apodini\/documentation\/Apodini\/Component","preciseIdentifier":"s:7Apodini9ComponentP","text":"Component"},{"kind":"text","text":", "},{"kind":"typeIdentifier","text":"T46"},{"kind":"text","text":" : "},{"kind":"typeIdentifier","identifier":"doc:\/\/Apodini\/documentation\/Apodini\/Component","preciseIdentifier":"s:7Apodini9ComponentP","text":"Component"},{"kind":"text","text":", "},{"kind":"typeIdentifier","text":"T47"},{"kind":"text","text":" : "},{"kind":"typeIdentifier","identifier":"doc:\/\/Apodini\/documentation\/Apodini\/Component","preciseIdentifier":"s:7Apodini9ComponentP","text":"Component"},{"kind":"text","text":", "},{"kind":"typeIdentifier","text":"T48"},{"kind":"text","text":" : "},{"kind":"typeIdentifier","identifier":"doc:\/\/Apodini\/documentation\/Apodini\/Component","preciseIdentifier":"s:7Apodini9ComponentP","text":"Component"},{"kind":"text","text":", "},{"kind":"typeIdentifier","text":"T49"},{"kind":"text","text":" : "},{"kind":"typeIdentifier","identifier":"doc:\/\/Apodini\/documentation\/Apodini\/Component","preciseIdentifier":"s:7Apodini9ComponentP","text":"Component"},{"kind":"text","text":", "},{"kind":"typeIdentifier","text":"T50"},{"kind":"text","text":" : "},{"kind":"typeIdentifier","identifier":"doc:\/\/Apodini\/documentation\/Apodini\/Component","preciseIdentifier":"s:7Apodini9ComponentP","text":"Component"},{"kind":"text","text":", "},{"kind":"typeIdentifier","text":"T51"},{"kind":"text","text":" : "},{"kind":"typeIdentifier","identifier":"doc:\/\/Apodini\/documentation\/Apodini\/Component","preciseIdentifier":"s:7Apodini9ComponentP","text":"Component"},{"kind":"text","text":", "},{"kind":"typeIdentifier","text":"T52"},{"kind":"text","text":" : "},{"kind":"typeIdentifier","identifier":"doc:\/\/Apodini\/documentation\/Apodini\/Component","preciseIdentifier":"s:7Apodini9ComponentP","text":"Component"},{"kind":"text","text":", "},{"kind":"typeIdentifier","text":"T53"},{"kind":"text","text":" : "},{"kind":"typeIdentifier","identifier":"doc:\/\/Apodini\/documentation\/Apodini\/Component","preciseIdentifier":"s:7Apodini9ComponentP","text":"Component"},{"kind":"text","text":", "},{"kind":"typeIdentifier","text":"T54"},{"kind":"text","text":" : "},{"kind":"typeIdentifier","identifier":"doc:\/\/Apodini\/documentation\/Apodini\/Component","preciseIdentifier":"s:7Apodini9ComponentP","text":"Component"},{"kind":"text","text":", "},{"kind":"typeIdentifier","text":"T55"},{"kind":"text","text":" : "},{"kind":"typeIdentifier","identifier":"doc:\/\/Apodini\/documentation\/Apodini\/Component","preciseIdentifier":"s:7Apodini9ComponentP","text":"Component"},{"kind":"text","text":", "},{"kind":"typeIdentifier","text":"T56"},{"kind":"text","text":" : "},{"kind":"typeIdentifier","identifier":"doc:\/\/Apodini\/documentation\/Apodini\/Component","preciseIdentifier":"s:7Apodini9ComponentP","text":"Component"},{"kind":"text","text":", "},{"kind":"typeIdentifier","text":"T57"},{"kind":"text","text":" : "},{"kind":"typeIdentifier","identifier":"doc:\/\/Apodini\/documentation\/Apodini\/Component","preciseIdentifier":"s:7Apodini9ComponentP","text":"Component"},{"kind":"text","text":", "},{"kind":"typeIdentifier","text":"T58"},{"kind":"text","text":" : "},{"kind":"typeIdentifier","identifier":"doc:\/\/Apodini\/documentation\/Apodini\/Component","preciseIdentifier":"s:7Apodini9ComponentP","text":"Component"},{"kind":"text","text":", "},{"kind":"typeIdentifier","text":"T59"},{"kind":"text","text":" : "},{"kind":"typeIdentifier","identifier":"doc:\/\/Apodini\/documentation\/Apodini\/Component","preciseIdentifier":"s:7Apodini9ComponentP","text":"Component"},{"kind":"text","text":"\n"}],"languages":["swift"],"platforms":["macOS"]}]}],"schemaVersion":{"major":0,"minor":3,"patch":0},"sections":[],"variants":[{"paths":["\/documentation\/apodini\/componentbuilder\/buildblock(_:_:_:_:_:_:_:_:_:_:_:_:_:_:_:_:_:_:_:_:_:_:_:_:_:_:_:_:_:_:_:_:_:_:_:_:_:_:_:_:_:_:_:_:_:_:_:_:_:_:_:_:_:_:_:_:_:_:_:_:)"],"traits":[{"interfaceLanguage":"swift"}]}],"identifier":{"url":"doc:\/\/Apodini\/documentation\/Apodini\/ComponentBuilder\/buildBlock(_:_:_:_:_:_:_:_:_:_:_:_:_:_:_:_:_:_:_:_:_:_:_:_:_:_:_:_:_:_:_:_:_:_:_:_:_:_:_:_:_:_:_:_:_:_:_:_:_:_:_:_:_:_:_:_:_:_:_:_:)","interfaceLanguage":"swift"},"kind":"symbol","metadata":{"fragments":[{"kind":"keyword","text":"static"},{"kind":"text","text":" "},{"kind":"keyword","text":"func"},{"kind":"text","text":" "},{"kind":"identifier","text":"buildBlock"},{"kind":"text","text":"<"},{"kind":"genericParameter","text":"T0"},{"kind":"text","text":", "},{"kind":"genericParameter","text":"T1"},{"kind":"text","text":", "},{"kind":"genericParameter","text":"T2"},{"kind":"text","text":", "},{"kind":"genericParameter","text":"T3"},{"kind":"text","text":", "},{"kind":"genericParameter","text":"T4"},{"kind":"text","text":", "},{"kind":"genericParameter","text":"T5"},{"kind":"text","text":", "},{"kind":"genericParameter","text":"T6"},{"kind":"text","text":", "},{"kind":"genericParameter","text":"T7"},{"kind":"text","text":", "},{"kind":"genericParameter","text":"T8"},{"kind":"text","text":", "},{"kind":"genericParameter","text":"T9"},{"kind":"text","text":", "},{"kind":"genericParameter","text":"T10"},{"kind":"text","text":", "},{"kind":"genericParameter","text":"T11"},{"kind":"text","text":", "},{"kind":"genericParameter","text":"T12"},{"kind":"text","text":", "},{"kind":"genericParameter","text":"T13"},{"kind":"text","text":", "},{"kind":"genericParameter","text":"T14"},{"kind":"text","text":", "},{"kind":"genericParameter","text":"T15"},{"kind":"text","text":", "},{"kind":"genericParameter","text":"T16"},{"kind":"text","text":", "},{"kind":"genericParameter","text":"T17"},{"kind":"text","text":", "},{"kind":"genericParameter","text":"T18"},{"kind":"text","text":", "},{"kind":"genericParameter","text":"T19"},{"kind":"text","text":", "},{"kind":"genericParameter","text":"T20"},{"kind":"text","text":", "},{"kind":"genericParameter","text":"T21"},{"kind":"text","text":", "},{"kind":"genericParameter","text":"T22"},{"kind":"text","text":", "},{"kind":"genericParameter","text":"T23"},{"kind":"text","text":", "},{"kind":"genericParameter","text":"T24"},{"kind":"text","text":", "},{"kind":"genericParameter","text":"T25"},{"kind":"text","text":", "},{"kind":"genericParameter","text":"T26"},{"kind":"text","text":", "},{"kind":"genericParameter","text":"T27"},{"kind":"text","text":", "},{"kind":"genericParameter","text":"T28"},{"kind":"text","text":", "},{"kind":"genericParameter","text":"T29"},{"kind":"text","text":", "},{"kind":"genericParameter","text":"T30"},{"kind":"text","text":", "},{"kind":"genericParameter","text":"T31"},{"kind":"text","text":", "},{"kind":"genericParameter","text":"T32"},{"kind":"text","text":", "},{"kind":"genericParameter","text":"T33"},{"kind":"text","text":", "},{"kind":"genericParameter","text":"T34"},{"kind":"text","text":", "},{"kind":"genericParameter","text":"T35"},{"kind":"text","text":", "},{"kind":"genericParameter","text":"T36"},{"kind":"text","text":", "},{"kind":"genericParameter","text":"T37"},{"kind":"text","text":", "},{"kind":"genericParameter","text":"T38"},{"kind":"text","text":", "},{"kind":"genericParameter","text":"T39"},{"kind":"text","text":", "},{"kind":"genericParameter","text":"T40"},{"kind":"text","text":", "},{"kind":"genericParameter","text":"T41"},{"kind":"text","text":", "},{"kind":"genericParameter","text":"T42"},{"kind":"text","text":", "},{"kind":"genericParameter","text":"T43"},{"kind":"text","text":", "},{"kind":"genericParameter","text":"T44"},{"kind":"text","text":", "},{"kind":"genericParameter","text":"T45"},{"kind":"text","text":", "},{"kind":"genericParameter","text":"T46"},{"kind":"text","text":", "},{"kind":"genericParameter","text":"T47"},{"kind":"text","text":", "},{"kind":"genericParameter","text":"T48"},{"kind":"text","text":", "},{"kind":"genericParameter","text":"T49"},{"kind":"text","text":", "},{"kind":"genericParameter","text":"T50"},{"kind":"text","text":", "},{"kind":"genericParameter","text":"T51"},{"kind":"text","text":", "},{"kind":"genericParameter","text":"T52"},{"kind":"text","text":", "},{"kind":"genericParameter","text":"T53"},{"kind":"text","text":", "},{"kind":"genericParameter","text":"T54"},{"kind":"text","text":", "},{"kind":"genericParameter","text":"T55"},{"kind":"text","text":", "},{"kind":"genericParameter","text":"T56"},{"kind":"text","text":", "},{"kind":"genericParameter","text":"T57"},{"kind":"text","text":", "},{"kind":"genericParameter","text":"T58"},{"kind":"text","text":", "},{"kind":"genericParameter","text":"T59"},{"kind":"text","text":">("},{"kind":"typeIdentifier","text":"T0"},{"kind":"text","text":", "},{"kind":"typeIdentifier","text":"T1"},{"kind":"text","text":", "},{"kind":"typeIdentifier","text":"T2"},{"kind":"text","text":", "},{"kind":"typeIdentifier","text":"T3"},{"kind":"text","text":", "},{"kind":"typeIdentifier","text":"T4"},{"kind":"text","text":", "},{"kind":"typeIdentifier","text":"T5"},{"kind":"text","text":", "},{"kind":"typeIdentifier","text":"T6"},{"kind":"text","text":", "},{"kind":"typeIdentifier","text":"T7"},{"kind":"text","text":", "},{"kind":"typeIdentifier","text":"T8"},{"kind":"text","text":", "},{"kind":"typeIdentifier","text":"T9"},{"kind":"text","text":", "},{"kind":"typeIdentifier","text":"T10"},{"kind":"text","text":", "},{"kind":"typeIdentifier","text":"T11"},{"kind":"text","text":", "},{"kind":"typeIdentifier","text":"T12"},{"kind":"text","text":", "},{"kind":"typeIdentifier","text":"T13"},{"kind":"text","text":", "},{"kind":"typeIdentifier","text":"T14"},{"kind":"text","text":", "},{"kind":"typeIdentifier","text":"T15"},{"kind":"text","text":", "},{"kind":"typeIdentifier","text":"T16"},{"kind":"text","text":", "},{"kind":"typeIdentifier","text":"T17"},{"kind":"text","text":", "},{"kind":"typeIdentifier","text":"T18"},{"kind":"text","text":", "},{"kind":"typeIdentifier","text":"T19"},{"kind":"text","text":", "},{"kind":"typeIdentifier","text":"T20"},{"kind":"text","text":", "},{"kind":"typeIdentifier","text":"T21"},{"kind":"text","text":", "},{"kind":"typeIdentifier","text":"T22"},{"kind":"text","text":", "},{"kind":"typeIdentifier","text":"T23"},{"kind":"text","text":", "},{"kind":"typeIdentifier","text":"T24"},{"kind":"text","text":", "},{"kind":"typeIdentifier","text":"T25"},{"kind":"text","text":", "},{"kind":"typeIdentifier","text":"T26"},{"kind":"text","text":", "},{"kind":"typeIdentifier","text":"T27"},{"kind":"text","text":", "},{"kind":"typeIdentifier","text":"T28"},{"kind":"text","text":", "},{"kind":"typeIdentifier","text":"T29"},{"kind":"text","text":", "},{"kind":"typeIdentifier","text":"T30"},{"kind":"text","text":", "},{"kind":"typeIdentifier","text":"T31"},{"kind":"text","text":", "},{"kind":"typeIdentifier","text":"T32"},{"kind":"text","text":", "},{"kind":"typeIdentifier","text":"T33"},{"kind":"text","text":", "},{"kind":"typeIdentifier","text":"T34"},{"kind":"text","text":", "},{"kind":"typeIdentifier","text":"T35"},{"kind":"text","text":", "},{"kind":"typeIdentifier","text":"T36"},{"kind":"text","text":", "},{"kind":"typeIdentifier","text":"T37"},{"kind":"text","text":", "},{"kind":"typeIdentifier","text":"T38"},{"kind":"text","text":", "},{"kind":"typeIdentifier","text":"T39"},{"kind":"text","text":", "},{"kind":"typeIdentifier","text":"T40"},{"kind":"text","text":", "},{"kind":"typeIdentifier","text":"T41"},{"kind":"text","text":", "},{"kind":"typeIdentifier","text":"T42"},{"kind":"text","text":", "},{"kind":"typeIdentifier","text":"T43"},{"kind":"text","text":", "},{"kind":"typeIdentifier","text":"T44"},{"kind":"text","text":", "},{"kind":"typeIdentifier","text":"T45"},{"kind":"text","text":", "},{"kind":"typeIdentifier","text":"T46"},{"kind":"text","text":", "},{"kind":"typeIdentifier","text":"T47"},{"kind":"text","text":", "},{"kind":"typeIdentifier","text":"T48"},{"kind":"text","text":", "},{"kind":"typeIdentifier","text":"T49"},{"kind":"text","text":", "},{"kind":"typeIdentifier","text":"T50"},{"kind":"text","text":", "},{"kind":"typeIdentifier","text":"T51"},{"kind":"text","text":", "},{"kind":"typeIdentifier","text":"T52"},{"kind":"text","text":", "},{"kind":"typeIdentifier","text":"T53"},{"kind":"text","text":", "},{"kind":"typeIdentifier","text":"T54"},{"kind":"text","text":", "},{"kind":"typeIdentifier","text":"T55"},{"kind":"text","text":", "},{"kind":"typeIdentifier","text":"T56"},{"kind":"text","text":", "},{"kind":"typeIdentifier","text":"T57"},{"kind":"text","text":", "},{"kind":"typeIdentifier","text":"T58"},{"kind":"text","text":", "},{"kind":"typeIdentifier","text":"T59"},{"kind":"text","text":") -> "},{"kind":"keyword","text":"some"},{"kind":"text","text":" "},{"kind":"typeIdentifier","text":"Component","preciseIdentifier":"s:7Apodini9ComponentP"}],"title":"buildBlock(_:_:_:_:_:_:_:_:_:_:_:_:_:_:_:_:_:_:_:_:_:_:_:_:_:_:_:_:_:_:_:_:_:_:_:_:_:_:_:_:_:_:_:_:_:_:_:_:_:_:_:_:_:_:_:_:_:_:_:_:)","roleHeading":"Type Method","role":"symbol","symbolKind":"method","externalID":"s:7Apodini16ComponentBuilderV10buildBlockyQrx_q_q0_q1_q2_q3_q4_q5_q6_q7_q8_q9_q10_q11_q12_q13_q14_q15_q16_q17_q18_q19_q20_q21_q22_q23_q24_q25_q26_q27_q28_q29_q30_q31_q32_q33_q34_q35_q36_q37_q38_q39_q40_q41_q42_q43_q44_q45_q46_q47_q48_q49_q50_q51_q52_q53_q54_q55_q56_q57_tAA0B0RzAaER_AaER0_AaER1_AaER2_AaER3_AaER4_AaER5_AaER6_AaER7_AaER8_AaER9_AaER10_AaER11_AaER12_AaER13_AaER14_AaER15_AaER16_AaER17_AaER18_AaER19_AaER20_AaER21_AaER22_AaER23_AaER24_AaER25_AaER26_AaER27_AaER28_AaER29_AaER30_AaER31_AaER32_AaER33_AaER34_AaER35_AaER36_AaER37_AaER38_AaER39_AaER40_AaER41_AaER42_AaER43_AaER44_AaER45_AaER46_AaER47_AaER48_AaER49_AaER50_AaER51_AaER52_AaER53_AaER54_AaER55_AaER56_AaER57_r58_lFZ","modules":[{"name":"Apodini"}]},"hierarchy":{"paths":[["doc:\/\/Apodini\/documentation\/Apodini","doc:\/\/Apodini\/documentation\/Apodini\/ComponentBuilder"]]},"references":{"doc://Apodini/documentation/Apodini":{"role":"collection","title":"Apodini","abstract":[{"type":"text","text":"A declarative, composable framework to build web services using Swift."}],"identifier":"doc:\/\/Apodini\/documentation\/Apodini","kind":"symbol","type":"topic","url":"\/documentation\/apodini"},"doc://Apodini/documentation/Apodini/ComponentBuilder":{"role":"symbol","title":"ComponentBuilder","fragments":[{"kind":"keyword","text":"struct"},{"kind":"text","text":" "},{"kind":"identifier","text":"ComponentBuilder"}],"abstract":[],"identifier":"doc:\/\/Apodini\/documentation\/Apodini\/ComponentBuilder","kind":"symbol","type":"topic","navigatorTitle":[{"kind":"identifier","text":"ComponentBuilder"}],"url":"\/documentation\/apodini\/componentbuilder"},"doc://Apodini/documentation/Apodini/Component":{"role":"symbol","title":"Component","fragments":[{"kind":"keyword","text":"protocol"},{"kind":"text","text":" "},{"kind":"identifier","text":"Component"}],"abstract":[{"type":"text","text":"A "},{"type":"codeVoice","code":"Component"},{"type":"text","text":" is the central building block of  Apodini. Each component handles a specific functionality of the Apodini web service."}],"identifier":"doc:\/\/Apodini\/documentation\/Apodini\/Component","kind":"symbol","type":"topic","navigatorTitle":[{"kind":"identifier","text":"Component"}],"url":"\/documentation\/apodini\/component"},"doc://Apodini/documentation/Apodini/ComponentBuilder/buildBlock(_:_:_:_:_:_:_:_:_:_:_:_:_:_:_:_:_:_:_:_:_:_:_:_:_:_:_:_:_:_:_:_:_:_:_:_:_:_:_:_:_:_:_:_:_:_:_:_:_:_:_:_:_:_:_:_:_:_:_:_:)":{"role":"symbol","title":"buildBlock(_:_:_:_:_:_:_:_:_:_:_:_:_:_:_:_:_:_:_:_:_:_:_:_:_:_:_:_:_:_:_:_:_:_:_:_:_:_:_:_:_:_:_:_:_:_:_:_:_:_:_:_:_:_:_:_:_:_:_:_:)","fragments":[{"kind":"keyword","text":"static"},{"kind":"text","text":" "},{"kind":"keyword","text":"func"},{"kind":"text","text":" "},{"kind":"identifier","text":"buildBlock"},{"kind":"text","text":"<"},{"kind":"genericParameter","text":"T0"},{"kind":"text","text":", "},{"kind":"genericParameter","text":"T1"},{"kind":"text","text":", "},{"kind":"genericParameter","text":"T2"},{"kind":"text","text":", "},{"kind":"genericParameter","text":"T3"},{"kind":"text","text":", "},{"kind":"genericParameter","text":"T4"},{"kind":"text","text":", "},{"kind":"genericParameter","text":"T5"},{"kind":"text","text":", "},{"kind":"genericParameter","text":"T6"},{"kind":"text","text":", "},{"kind":"genericParameter","text":"T7"},{"kind":"text","text":", "},{"kind":"genericParameter","text":"T8"},{"kind":"text","text":", "},{"kind":"genericParameter","text":"T9"},{"kind":"text","text":", "},{"kind":"genericParameter","text":"T10"},{"kind":"text","text":", "},{"kind":"genericParameter","text":"T11"},{"kind":"text","text":", "},{"kind":"genericParameter","text":"T12"},{"kind":"text","text":", "},{"kind":"genericParameter","text":"T13"},{"kind":"text","text":", "},{"kind":"genericParameter","text":"T14"},{"kind":"text","text":", "},{"kind":"genericParameter","text":"T15"},{"kind":"text","text":", "},{"kind":"genericParameter","text":"T16"},{"kind":"text","text":", "},{"kind":"genericParameter","text":"T17"},{"kind":"text","text":", "},{"kind":"genericParameter","text":"T18"},{"kind":"text","text":", "},{"kind":"genericParameter","text":"T19"},{"kind":"text","text":", "},{"kind":"genericParameter","text":"T20"},{"kind":"text","text":", "},{"kind":"genericParameter","text":"T21"},{"kind":"text","text":", "},{"kind":"genericParameter","text":"T22"},{"kind":"text","text":", "},{"kind":"genericParameter","text":"T23"},{"kind":"text","text":", "},{"kind":"genericParameter","text":"T24"},{"kind":"text","text":", "},{"kind":"genericParameter","text":"T25"},{"kind":"text","text":", "},{"kind":"genericParameter","text":"T26"},{"kind":"text","text":", "},{"kind":"genericParameter","text":"T27"},{"kind":"text","text":", "},{"kind":"genericParameter","text":"T28"},{"kind":"text","text":", "},{"kind":"genericParameter","text":"T29"},{"kind":"text","text":", "},{"kind":"genericParameter","text":"T30"},{"kind":"text","text":", "},{"kind":"genericParameter","text":"T31"},{"kind":"text","text":", "},{"kind":"genericParameter","text":"T32"},{"kind":"text","text":", "},{"kind":"genericParameter","text":"T33"},{"kind":"text","text":", "},{"kind":"genericParameter","text":"T34"},{"kind":"text","text":", "},{"kind":"genericParameter","text":"T35"},{"kind":"text","text":", "},{"kind":"genericParameter","text":"T36"},{"kind":"text","text":", "},{"kind":"genericParameter","text":"T37"},{"kind":"text","text":", "},{"kind":"genericParameter","text":"T38"},{"kind":"text","text":", "},{"kind":"genericParameter","text":"T39"},{"kind":"text","text":", "},{"kind":"genericParameter","text":"T40"},{"kind":"text","text":", "},{"kind":"genericParameter","text":"T41"},{"kind":"text","text":", "},{"kind":"genericParameter","text":"T42"},{"kind":"text","text":", "},{"kind":"genericParameter","text":"T43"},{"kind":"text","text":", "},{"kind":"genericParameter","text":"T44"},{"kind":"text","text":", "},{"kind":"genericParameter","text":"T45"},{"kind":"text","text":", "},{"kind":"genericParameter","text":"T46"},{"kind":"text","text":", "},{"kind":"genericParameter","text":"T47"},{"kind":"text","text":", "},{"kind":"genericParameter","text":"T48"},{"kind":"text","text":", "},{"kind":"genericParameter","text":"T49"},{"kind":"text","text":", "},{"kind":"genericParameter","text":"T50"},{"kind":"text","text":", "},{"kind":"genericParameter","text":"T51"},{"kind":"text","text":", "},{"kind":"genericParameter","text":"T52"},{"kind":"text","text":", "},{"kind":"genericParameter","text":"T53"},{"kind":"text","text":", "},{"kind":"genericParameter","text":"T54"},{"kind":"text","text":", "},{"kind":"genericParameter","text":"T55"},{"kind":"text","text":", "},{"kind":"genericParameter","text":"T56"},{"kind":"text","text":", "},{"kind":"genericParameter","text":"T57"},{"kind":"text","text":", "},{"kind":"genericParameter","text":"T58"},{"kind":"text","text":", "},{"kind":"genericParameter","text":"T59"},{"kind":"text","text":">("},{"kind":"typeIdentifier","text":"T0"},{"kind":"text","text":", "},{"kind":"typeIdentifier","text":"T1"},{"kind":"text","text":", "},{"kind":"typeIdentifier","text":"T2"},{"kind":"text","text":", "},{"kind":"typeIdentifier","text":"T3"},{"kind":"text","text":", "},{"kind":"typeIdentifier","text":"T4"},{"kind":"text","text":", "},{"kind":"typeIdentifier","text":"T5"},{"kind":"text","text":", "},{"kind":"typeIdentifier","text":"T6"},{"kind":"text","text":", "},{"kind":"typeIdentifier","text":"T7"},{"kind":"text","text":", "},{"kind":"typeIdentifier","text":"T8"},{"kind":"text","text":", "},{"kind":"typeIdentifier","text":"T9"},{"kind":"text","text":", "},{"kind":"typeIdentifier","text":"T10"},{"kind":"text","text":", "},{"kind":"typeIdentifier","text":"T11"},{"kind":"text","text":", "},{"kind":"typeIdentifier","text":"T12"},{"kind":"text","text":", "},{"kind":"typeIdentifier","text":"T13"},{"kind":"text","text":", "},{"kind":"typeIdentifier","text":"T14"},{"kind":"text","text":", "},{"kind":"typeIdentifier","text":"T15"},{"kind":"text","text":", "},{"kind":"typeIdentifier","text":"T16"},{"kind":"text","text":", "},{"kind":"typeIdentifier","text":"T17"},{"kind":"text","text":", "},{"kind":"typeIdentifier","text":"T18"},{"kind":"text","text":", "},{"kind":"typeIdentifier","text":"T19"},{"kind":"text","text":", "},{"kind":"typeIdentifier","text":"T20"},{"kind":"text","text":", "},{"kind":"typeIdentifier","text":"T21"},{"kind":"text","text":", "},{"kind":"typeIdentifier","text":"T22"},{"kind":"text","text":", "},{"kind":"typeIdentifier","text":"T23"},{"kind":"text","text":", "},{"kind":"typeIdentifier","text":"T24"},{"kind":"text","text":", "},{"kind":"typeIdentifier","text":"T25"},{"kind":"text","text":", "},{"kind":"typeIdentifier","text":"T26"},{"kind":"text","text":", "},{"kind":"typeIdentifier","text":"T27"},{"kind":"text","text":", "},{"kind":"typeIdentifier","text":"T28"},{"kind":"text","text":", "},{"kind":"typeIdentifier","text":"T29"},{"kind":"text","text":", "},{"kind":"typeIdentifier","text":"T30"},{"kind":"text","text":", "},{"kind":"typeIdentifier","text":"T31"},{"kind":"text","text":", "},{"kind":"typeIdentifier","text":"T32"},{"kind":"text","text":", "},{"kind":"typeIdentifier","text":"T33"},{"kind":"text","text":", "},{"kind":"typeIdentifier","text":"T34"},{"kind":"text","text":", "},{"kind":"typeIdentifier","text":"T35"},{"kind":"text","text":", "},{"kind":"typeIdentifier","text":"T36"},{"kind":"text","text":", "},{"kind":"typeIdentifier","text":"T37"},{"kind":"text","text":", "},{"kind":"typeIdentifier","text":"T38"},{"kind":"text","text":", "},{"kind":"typeIdentifier","text":"T39"},{"kind":"text","text":", "},{"kind":"typeIdentifier","text":"T40"},{"kind":"text","text":", "},{"kind":"typeIdentifier","text":"T41"},{"kind":"text","text":", "},{"kind":"typeIdentifier","text":"T42"},{"kind":"text","text":", "},{"kind":"typeIdentifier","text":"T43"},{"kind":"text","text":", "},{"kind":"typeIdentifier","text":"T44"},{"kind":"text","text":", "},{"kind":"typeIdentifier","text":"T45"},{"kind":"text","text":", "},{"kind":"typeIdentifier","text":"T46"},{"kind":"text","text":", "},{"kind":"typeIdentifier","text":"T47"},{"kind":"text","text":", "},{"kind":"typeIdentifier","text":"T48"},{"kind":"text","text":", "},{"kind":"typeIdentifier","text":"T49"},{"kind":"text","text":", "},{"kind":"typeIdentifier","text":"T50"},{"kind":"text","text":", "},{"kind":"typeIdentifier","text":"T51"},{"kind":"text","text":", "},{"kind":"typeIdentifier","text":"T52"},{"kind":"text","text":", "},{"kind":"typeIdentifier","text":"T53"},{"kind":"text","text":", "},{"kind":"typeIdentifier","text":"T54"},{"kind":"text","text":", "},{"kind":"typeIdentifier","text":"T55"},{"kind":"text","text":", "},{"kind":"typeIdentifier","text":"T56"},{"kind":"text","text":", "},{"kind":"typeIdentifier","text":"T57"},{"kind":"text","text":", "},{"kind":"typeIdentifier","text":"T58"},{"kind":"text","text":", "},{"kind":"typeIdentifier","text":"T59"},{"kind":"text","text":") -> "},{"kind":"keyword","text":"some"},{"kind":"text","text":" "},{"kind":"typeIdentifier","text":"Component","preciseIdentifier":"s:7Apodini9ComponentP"}],"abstract":[],"identifier":"doc:\/\/Apodini\/documentation\/Apodini\/ComponentBuilder\/buildBlock(_:_:_:_:_:_:_:_:_:_:_:_:_:_:_:_:_:_:_:_:_:_:_:_:_:_:_:_:_:_:_:_:_:_:_:_:_:_:_:_:_:_:_:_:_:_:_:_:_:_:_:_:_:_:_:_:_:_:_:_:)","kind":"symbol","type":"topic","url":"\/documentation\/apodini\/componentbuilder\/buildblock(_:_:_:_:_:_:_:_:_:_:_:_:_:_:_:_:_:_:_:_:_:_:_:_:_:_:_:_:_:_:_:_:_:_:_:_:_:_:_:_:_:_:_:_:_:_:_:_:_:_:_:_:_:_:_:_:_:_:_:_:)"}}}